{"chunk_definitions":[{"row":14,"row_count":1,"visible":true,"expansion_state":0,"options":{"engine":"r","label":"unnamed-chunk-8"},"document_id":"48812289","chunk_id":"c0s4cyanc6lec","chunk_label":"unnamed-chunk-1"},{"row":18,"row_count":1,"visible":true,"expansion_state":0,"options":{"engine":"r","label":"unnamed-chunk-9"},"document_id":"48812289","chunk_id":"cfz8bxe49pizj","chunk_label":"unnamed-chunk-2"},{"row":22,"row_count":1,"visible":true,"expansion_state":0,"options":{"engine":"r","label":"unnamed-chunk-10"},"document_id":"48812289","chunk_id":"cug9rh8d388p4","chunk_label":"unnamed-chunk-3"},{"row":32,"row_count":1,"visible":true,"expansion_state":0,"options":{"engine":"r","label":"unnamed-chunk-11"},"document_id":"48812289","chunk_id":"cyzxuip3lk13m","chunk_label":"unnamed-chunk-4"},{"row":36,"row_count":1,"visible":true,"expansion_state":0,"options":{"engine":"r","label":"unnamed-chunk-12"},"document_id":"48812289","chunk_id":"cn5xa5wej289g","chunk_label":"unnamed-chunk-5"},{"row":40,"row_count":1,"visible":true,"expansion_state":0,"options":{"engine":"r","label":"unnamed-chunk-13"},"document_id":"48812289","chunk_id":"cz8zju54idyay","chunk_label":"unnamed-chunk-6"},{"row":47,"row_count":1,"visible":true,"expansion_state":0,"options":{"engine":"r","label":"unnamed-chunk-14"},"document_id":"48812289","chunk_id":"c51kxphyag5v9","chunk_label":"unnamed-chunk-7"},{"row":51,"row_count":1,"visible":true,"expansion_state":0,"options":{"engine":"r","label":"unnamed-chunk-15"},"document_id":"48812289","chunk_id":"csfn4vzx9jsyj","chunk_label":"unnamed-chunk-8"},{"row":58,"row_count":1,"visible":true,"expansion_state":0,"options":{"engine":"r","label":"unnamed-chunk-16"},"document_id":"48812289","chunk_id":"cn3s9emzaz6qc","chunk_label":"unnamed-chunk-9"},{"row":65,"row_count":1,"visible":true,"expansion_state":0,"options":{"engine":"r","label":"unnamed-chunk-17"},"document_id":"48812289","chunk_id":"c1e8xagc4nctb","chunk_label":"unnamed-chunk-10"},{"row":71,"row_count":1,"visible":true,"expansion_state":0,"options":{"engine":"r","label":"unnamed-chunk-18"},"document_id":"48812289","chunk_id":"cir132hbdbykk","chunk_label":"unnamed-chunk-11"},{"row":77,"row_count":1,"visible":true,"expansion_state":0,"options":{"engine":"r","label":"unnamed-chunk-19"},"document_id":"48812289","chunk_id":"c4sn3voirvc9s","chunk_label":"unnamed-chunk-12"},{"row":81,"row_count":1,"visible":true,"expansion_state":0,"options":{"engine":"r","label":"unnamed-chunk-20"},"document_id":"48812289","chunk_id":"cmogqlal06jtq","chunk_label":"unnamed-chunk-13"},{"row":88,"row_count":1,"visible":true,"expansion_state":0,"options":{"engine":"r","label":"unnamed-chunk-21"},"document_id":"48812289","chunk_id":"c2rerpcklp2pa","chunk_label":"unnamed-chunk-14"},{"row":94,"row_count":1,"visible":true,"expansion_state":0,"options":{"engine":"r","label":"unnamed-chunk-22"},"document_id":"48812289","chunk_id":"co0ohgegq1ail","chunk_label":"unnamed-chunk-15"},{"row":98,"row_count":1,"visible":true,"expansion_state":0,"options":{"engine":"r","label":"unnamed-chunk-23"},"document_id":"48812289","chunk_id":"cgf5srrkx07tt","chunk_label":"unnamed-chunk-16"},{"row":102,"row_count":1,"visible":true,"expansion_state":0,"options":{"engine":"r","label":"unnamed-chunk-24"},"document_id":"48812289","chunk_id":"cigsbjfhhqu1c","chunk_label":"unnamed-chunk-17"},{"row":109,"row_count":1,"visible":true,"expansion_state":0,"options":{"engine":"r","label":"unnamed-chunk-25"},"document_id":"48812289","chunk_id":"cc4twdkqsa6wf","chunk_label":"unnamed-chunk-18"},{"row":116,"row_count":1,"visible":true,"expansion_state":0,"options":{"engine":"r","label":"unnamed-chunk-26"},"document_id":"48812289","chunk_id":"csjzg1gwfg20b","chunk_label":"unnamed-chunk-19"},{"row":123,"row_count":1,"visible":true,"expansion_state":0,"options":{"engine":"r","label":"unnamed-chunk-27"},"document_id":"48812289","chunk_id":"comxf0xu33f19","chunk_label":"unnamed-chunk-20"},{"row":127,"row_count":1,"visible":true,"expansion_state":0,"options":{"engine":"r","label":"unnamed-chunk-28"},"document_id":"48812289","chunk_id":"ca2gu1xu4px03","chunk_label":"unnamed-chunk-21"},{"row":131,"row_count":1,"visible":true,"expansion_state":0,"options":{"engine":"r","label":"unnamed-chunk-29"},"document_id":"48812289","chunk_id":"c36ktj7pk7a6z","chunk_label":"unnamed-chunk-22"},{"row":135,"row_count":1,"visible":true,"expansion_state":0,"options":{"engine":"r","label":"unnamed-chunk-30"},"document_id":"48812289","chunk_id":"cicm7yog8u1b2","chunk_label":"unnamed-chunk-23"},{"row":139,"row_count":1,"visible":true,"expansion_state":0,"options":{"engine":"r","label":"unnamed-chunk-31"},"document_id":"48812289","chunk_id":"csp3lxr0znwc9","chunk_label":"unnamed-chunk-24"},{"row":143,"row_count":1,"visible":true,"expansion_state":0,"options":{"engine":"r","label":"unnamed-chunk-32"},"document_id":"48812289","chunk_id":"cxb1bvpt75ura","chunk_label":"unnamed-chunk-25"},{"row":150,"row_count":1,"visible":true,"expansion_state":0,"options":{"engine":"r","label":"unnamed-chunk-33"},"document_id":"48812289","chunk_id":"cezfxh7tq7euf","chunk_label":"unnamed-chunk-26"},{"row":157,"row_count":1,"visible":true,"expansion_state":0,"options":{"engine":"r","label":"unnamed-chunk-34"},"document_id":"48812289","chunk_id":"cs5fn59e9yq5j","chunk_label":"unnamed-chunk-27"},{"row":164,"row_count":1,"visible":true,"expansion_state":0,"options":{"engine":"r","label":"unnamed-chunk-35"},"document_id":"48812289","chunk_id":"c0fpbn93igten","chunk_label":"unnamed-chunk-28"},{"row":170,"row_count":1,"visible":true,"expansion_state":0,"options":{"engine":"r","label":"unnamed-chunk-36"},"document_id":"48812289","chunk_id":"ckcv30zakuy9s","chunk_label":"unnamed-chunk-29"},{"row":174,"row_count":1,"visible":true,"expansion_state":0,"options":{"engine":"r","label":"unnamed-chunk-37"},"document_id":"48812289","chunk_id":"cnat507xjh842","chunk_label":"unnamed-chunk-30"},{"row":181,"row_count":1,"visible":true,"expansion_state":0,"options":{"engine":"r","label":"unnamed-chunk-38"},"document_id":"48812289","chunk_id":"ccajprtyg70ff","chunk_label":"unnamed-chunk-31"},{"row":187,"row_count":1,"visible":true,"expansion_state":0,"options":{"engine":"r","label":"unnamed-chunk-39"},"document_id":"48812289","chunk_id":"cgcihpssqj7aw","chunk_label":"unnamed-chunk-32"}],"doc_write_time":1698439019}